demo/__init__.py
demo/pub.py
demo/run.py
demo/pages/__init__.py
demo/pages/adr_page.py
demo/pages/image_page.py
demo/pages/ios_page.py
demo/pages/ocr_page.py
demo/pages/web_page.py
demo/tests/__init__.py
demo/tests/test_adr.py
demo/tests/test_api.py
demo/tests/test_ios.py
demo/tests/test_ocr.py
demo/tests/test_web.py
krunner/__init__.py
krunner/case.py
krunner/cli.py
krunner/page.py
krunner/scaffold.py
krunner/core/__init__.py
krunner/core/android/__init__.py
krunner/core/android/driver.py
krunner/core/android/element.py
krunner/core/api/__init__.py
krunner/core/api/request.py
krunner/core/image/__init__.py
krunner/core/image/driver.py
krunner/core/image/element.py
krunner/core/ios/__init__.py
krunner/core/ios/driver.py
krunner/core/ios/element.py
krunner/core/ocr/__init__.py
krunner/core/ocr/driver.py
krunner/core/ocr/element.py
krunner/core/web/__init__.py
krunner/core/web/driver.py
krunner/core/web/element.py
krunner/running/__init__.py
krunner/running/conf.yml
krunner/running/runner.py
krunner/testdata/__init__.py
krunner/testdata/data.py
krunner/utils/__init__.py
krunner/utils/allure_util.py
krunner/utils/common.py
krunner/utils/config.py
krunner/utils/des_util.py
krunner/utils/dingtalk.py
krunner/utils/excel.py
krunner/utils/exceptions.py
krunner/utils/log.py
krunner/utils/mail.py
krunner/utils/mysql_util.py
krunner/utils/pytest_util.py
krunner/utils/swagger_util.py
krunner-0.0.2.dist-info/METADATA
krunner-0.0.2.dist-info/WHEEL
krunner-0.0.2.dist-info/entry_points.txt
krunner-0.0.2.dist-info/top_level.txt
krunner-0.0.2.dist-info/RECORD
